CHANGES.rst
MANIFEST.in
README.md
requirements.txt
setup.cfg
setup.py
bin/__init__.py
bin/conf.py
bin/convert_xmls_to_jsons.py
bin/generate_xml_responses.py
python_kemptech_api/__init__.py
python_kemptech_api/api_xml.py
python_kemptech_api/capabilities.py
python_kemptech_api/client.py
python_kemptech_api/exceptions.py
python_kemptech_api/generic.py
python_kemptech_api/lxml_to_dict.py
python_kemptech_api/models.py
python_kemptech_api/objects.py
python_kemptech_api/utils.py
python_kemptech_api.egg-info/PKG-INFO
python_kemptech_api.egg-info/SOURCES.txt
python_kemptech_api.egg-info/dependency_links.txt
python_kemptech_api.egg-info/requires.txt
python_kemptech_api.egg-info/top_level.txt
tests/__init__.py
tests/integration/__init__.py
tests/integration/test_compat.py
tests/integration/test_xml_to_json.py
tests/integration/fixtures/__init__.py
tests/unit/__init__.py
tests/unit/test_api_xml.py
tests/unit/test_build_virtual_service.py
tests/unit/test_client.py
tests/unit/test_exceptions.py
tests/unit/test_kemp_base_object_model.py
tests/unit/test_loadmaster.py
tests/unit/test_real_server.py
tests/unit/test_utils.py
tests/unit/test_virtual_service.py