Metadata-Version: 1.2
Name: python-kemptech-api
Version: 0.7.42
Summary: KEMP Technologies Python API
Home-page: http://pypi.python.org/pypi/python-kemptech-api/
Author: KEMP Technologies
Author-email: smcgough@kemptechnologies.com
Maintainer: Shane McGough
Maintainer-email: smcgough@kemptechnologies.com,aconti@kemptechnologis.com,spower@kemptechnologies.com
License: Apache
Keywords: python api kemptech kemp technologies restfull loadmaster
Platform: UNKNOWN
Classifier: License :: OSI Approved :: Apache Software License
Classifier: Operating System :: POSIX
Classifier: Programming Language :: Python
Classifier: Programming Language :: Python :: 2.7
Classifier: Programming Language :: Python :: 3
Classifier: Topic :: Internet
